ppinot4py/__init__.py
ppinot4py/computers/__init__.py
ppinot4py/computers/conditions_computer.py
ppinot4py/computers/metrics_computer.py
ppinot4py/computers/tests/__init__.py
ppinot4py/computers/tests/test_conditions_computer.py
ppinot4py/computers/tests/test_metrics_computer.py
ppinot4py/model/__init__.py
ppinot4py/model/conditions.py
ppinot4py/model/measures.py
ppinot4py/model/states.py
ppinot4py/model/tests/__init__.py
ppinot4py/model/tests/test_measures.py
ppinot4py-1.2.1.dist-info/LICENSE
ppinot4py-1.2.1.dist-info/METADATA
ppinot4py-1.2.1.dist-info/WHEEL
ppinot4py-1.2.1.dist-info/top_level.txt
ppinot4py-1.2.1.dist-info/RECORD
