Metadata-Version: 2.1
Name: ppinot4py
Version: 1.2.1
Summary: PPINOT for Python (ppinot4py)
Home-page: https://github.com/isa-group/ppinot4py
Author: ISA Group
Author-email: resinas@us.es
License: GPL 3.0
Classifier: Programming Language :: Python :: 3
Classifier: License :: OSI Approved :: GNU General Public License v3 (GPLv3)
Classifier: Operating System :: OS Independent
Requires-Python: >=3.6
License-File: LICENSE
Requires-Dist: pandas
Requires-Dist: numpy
Requires-Dist: business-duration
